quayio_sdk/__init__.py
quayio_sdk/api_client.py
quayio_sdk/configuration.py
quayio_sdk/rest.py
quayio_sdk/api/__init__.py
quayio_sdk/api/billing_api.py
quayio_sdk/api/build_api.py
quayio_sdk/api/discovery_api.py
quayio_sdk/api/error_api.py
quayio_sdk/api/globalmessages_api.py
quayio_sdk/api/logs_api.py
quayio_sdk/api/manifest_api.py
quayio_sdk/api/organization_api.py
quayio_sdk/api/permission_api.py
quayio_sdk/api/prototype_api.py
quayio_sdk/api/repository_api.py
quayio_sdk/api/repositorynotification_api.py
quayio_sdk/api/repotoken_api.py
quayio_sdk/api/robot_api.py
quayio_sdk/api/search_api.py
quayio_sdk/api/secscan_api.py
quayio_sdk/api/tag_api.py
quayio_sdk/api/team_api.py
quayio_sdk/api/trigger_api.py
quayio_sdk/api/user_api.py
quayio_sdk/models/__init__.py
quayio_sdk/models/add_label.py
quayio_sdk/models/api_error.py
quayio_sdk/models/api_error_description.py
quayio_sdk/models/build_trigger_activate_request.py
quayio_sdk/models/change_tag.py
quayio_sdk/models/change_visibility.py
quayio_sdk/models/create_message.py
quayio_sdk/models/create_message_message.py
quayio_sdk/models/create_robot.py
quayio_sdk/models/export_logs.py
quayio_sdk/models/new_app.py
quayio_sdk/models/new_org.py
quayio_sdk/models/new_prototype.py
quayio_sdk/models/new_prototype_activating_user.py
quayio_sdk/models/new_prototype_delegate.py
quayio_sdk/models/new_repo.py
quayio_sdk/models/new_starred_repository.py
quayio_sdk/models/new_token.py
quayio_sdk/models/notification_create_request.py
quayio_sdk/models/prototype_update.py
quayio_sdk/models/repo_update.py
quayio_sdk/models/repository_build_request.py
quayio_sdk/models/restore_tag.py
quayio_sdk/models/run_parameters.py
quayio_sdk/models/team_description.py
quayio_sdk/models/team_permission.py
quayio_sdk/models/token_permission.py
quayio_sdk/models/update_app.py
quayio_sdk/models/update_org.py
quayio_sdk/models/update_trigger.py
quayio_sdk/models/update_user.py
quayio_sdk/models/user_permission.py
quayio_sdk/models/user_view.py
quayio_sdk-1.0.0.dist-info/METADATA
quayio_sdk-1.0.0.dist-info/WHEEL
quayio_sdk-1.0.0.dist-info/top_level.txt
quayio_sdk-1.0.0.dist-info/RECORD
