Metadata-Version: 2.1
Name: quayio-sdk
Version: 1.0.0
Summary: Quay Frontend
Home-page: 
Author-email: support@quay.io
Keywords: Swagger,Quay Frontend
Requires-Dist: certifi >=2017.4.17
Requires-Dist: python-dateutil >=2.1
Requires-Dist: six >=1.10
Requires-Dist: urllib3 >=1.23
